utca/.DS_Store
utca/core/.DS_Store
utca/core/__init__.py
utca/core/constants.py
utca/core/exceptions.py
utca/core/executable_level_1/.DS_Store
utca/core/executable_level_1/README.md
utca/core/executable_level_1/__init__.py
utca/core/executable_level_1/actions.py
utca/core/executable_level_1/component.py
utca/core/executable_level_1/eval.py
utca/core/executable_level_1/executable.py
utca/core/executable_level_1/executor.py
utca/core/executable_level_1/interpreter.py
utca/core/executable_level_1/memory.py
utca/core/executable_level_1/schema.py
utca/core/executable_level_1/utils.py
utca/core/predictor_level_2/README.md
utca/core/predictor_level_2/__init__.py
utca/core/predictor_level_2/add.txt
utca/core/predictor_level_2/predictor.py
utca/core/task_level_3/README.md
utca/core/task_level_3/__init__.py
utca/core/task_level_3/objects/objects.py
utca/core/task_level_3/schema.py
utca/core/task_level_3/task.py
utca/core/visualizer_level_2/base.py
utca/implementation/__init__.py
utca/implementation/apis/__init__.py
utca/implementation/apis/google_cloud/__init__.py
utca/implementation/apis/google_cloud/client.py
utca/implementation/apis/google_cloud/schema.py
utca/implementation/conditions/__init__.py
utca/implementation/conditions/pattern/__init__.py
utca/implementation/conditions/pattern/main.py
utca/implementation/conditions/semantic/embedding.py
utca/implementation/datasources/__init__.py
utca/implementation/datasources/audio/__init__.py
utca/implementation/datasources/audio/actions.py
utca/implementation/datasources/db/__init__.py
utca/implementation/datasources/db/chroma/__init__.py
utca/implementation/datasources/db/chroma/main.py
utca/implementation/datasources/db/chroma/schema.py
utca/implementation/datasources/db/neo4j/__init__.py
utca/implementation/datasources/db/neo4j/main.py
utca/implementation/datasources/db/qdrant/__init__.py
utca/implementation/datasources/db/qdrant/main.py
utca/implementation/datasources/db/sqlalchemy/__init__.py
utca-0.1.3.dist-info/LICENSE
utca-0.1.3.dist-info/METADATA
utca-0.1.3.dist-info/WHEEL
utca-0.1.3.dist-info/RECORD
