Metadata-Version: 2.1
Name: utca
Version: 0.1.3
Summary: 
Author: knowledgator.com
Requires-Python: >=3.9,<3.13
Classifier: Programming Language :: Python :: 3
Classifier: Programming Language :: Python :: 3.9
Classifier: Programming Language :: Python :: 3.10
Classifier: Programming Language :: Python :: 3.11
Classifier: Programming Language :: Python :: 3.12
Requires-Dist: accelerate (>=0.31.0,<0.32.0)
Requires-Dist: chromadb (>=0.5.0,<0.6.0)
Requires-Dist: cython (>=3.0.10,<4.0.0)
Requires-Dist: fastembed (>=0.3.0,<0.4.0)
Requires-Dist: gliner (>=0.2.2,<0.3.0)
Requires-Dist: google-api-python-client (>=2.116.0,<3.0.0)
Requires-Dist: google-auth-httplib2 (>=0.2.0,<0.3.0)
Requires-Dist: google-auth-oauthlib (>=1.2.0,<2.0.0)
Requires-Dist: lxml[html-clean] (>=5.2.2,<6.0.0)
Requires-Dist: neo4j (>=5.20.0,<6.0.0)
Requires-Dist: nltk (>=3.8.2,<4.0.0)
Requires-Dist: numpy (>=1.26.4,<2.0.0)
Requires-Dist: openai (>=1.29.0,<2.0.0)
Requires-Dist: openai-whisper (>=20231117,<20231118)
Requires-Dist: opencv-python (>=4.9.0.80,<5.0.0.0)
Requires-Dist: pdfplumber (>=0.11.0,<0.12.0)
Requires-Dist: pillow (>=10.3.0,<11.0.0)
Requires-Dist: pydantic (>=2.6.1,<3.0.0)
Requires-Dist: qdrant-client (>=1.9.1,<2.0.0)
Requires-Dist: reportlab (>=4.2.0,<5.0.0)
Requires-Dist: requests (>=2.32.2,<3.0.0)
Requires-Dist: requests-html (>=0.10.0,<0.11.0)
Requires-Dist: safetensors (>=0.4.3,<0.5.0)
Requires-Dist: soundfile (>=0.12.1,<0.13.0)
Requires-Dist: sqlalchemy (>=2.0.30,<3.0.0)
Requires-Dist: torch (>=2.0.0,<3.0.0)
Requires-Dist: transformers (>=4.37.2,<5.0.0)
